fastshot/__init__.py
fastshot/__version__.py
fastshot/_config_reset.ini
fastshot/ask_dialog copy.py
fastshot/ask_dialog.py
fastshot/async_operations.py
fastshot/cloud_sync.py
fastshot/config.ini
fastshot/enhanced_save_dialog.py
fastshot/env.bat
fastshot/gpt4o.py
fastshot/image_window.py
fastshot/main.py
fastshot/meta_cache.py
fastshot/notes_cache.py
fastshot/notes_manager.py
fastshot/paint_tool.py
fastshot/plugin_ask.py
fastshot/plugin_ocr.py
fastshot/quick_notes_ui.py
fastshot/screen_pen.py
fastshot/session_manager.py
fastshot/session_manager_ui.py
fastshot/snipping_tool.py
fastshot/text_tool.py
fastshot/tt.py
fastshot/window_control.py
fastshot/plugins/plugin_hello_world.py
fastshot/plugins/plugin_hyder.py
fastshot/plugins/plugin_mini.py
fastshot/plugins/plugin_retriver.py
fastshot/plugins/utils/__init__.py
fastshot/plugins/utils/hyder.py
fastshot/resources/ai_icon.png
fastshot/resources/close_icon.png
fastshot/resources/minimize_icon.png
fastshot/resources/paddleocr.zip
fastshot/resources/shortcuts.png
fastshot/resources/shortcuts1.png
fastshot/resources/title_icon.png
fastshot/resources/tk_color_chart.png
fastshot/resources/user_icon.png
fastshot/settings/__init__.py
fastshot/settings/settings_manager.py
fastshot/settings/settings_window.py
fastshot/settings/components/genai_frame.py
fastshot/settings/components/screenpen_frame.py
fastshot/settings/components/shortcuts_frame.py
fastshot/settings/utils/hotkey_capture.py
fastshot/utils/llm_utils.py
fastshot-1.5.0.dist-info/licenses/LICENSE
fastshot-1.5.0.dist-info/METADATA
fastshot-1.5.0.dist-info/WHEEL
fastshot-1.5.0.dist-info/entry_points.txt
fastshot-1.5.0.dist-info/top_level.txt
fastshot-1.5.0.dist-info/RECORD
