Metadata-Version: 2.4
Name: fastshot
Version: 1.5.0
Summary: A versatile screen capturing tool with annotation and OCR features
Home-page: https://github.com/jimeverest/fastshot
Author: Jim T
Author-email: tianwai263@gmail.com
Classifier: Programming Language :: Python :: 3
Classifier: License :: OSI Approved :: MIT License
Classifier: Operating System :: OS Independent
Requires-Python: >=3.7
License-File: LICENSE
Requires-Dist: pyautogui
Requires-Dist: pynput
Requires-Dist: pillow
Requires-Dist: screeninfo
Requires-Dist: mss
Requires-Dist: Pillow
Requires-Dist: pyperclip
Requires-Dist: pywin32
Requires-Dist: paddleocr
Requires-Dist: paddlepaddle
Requires-Dist: customtkinter
Requires-Dist: flask
Requires-Dist: configparser
Requires-Dist: openai
Requires-Dist: httpx>=0.24.0
Dynamic: author
Dynamic: author-email
Dynamic: classifier
Dynamic: description
Dynamic: description-content-type
Dynamic: home-page
Dynamic: license-file
Dynamic: requires-dist
Dynamic: requires-python
Dynamic: summary
